flask_sspi/__init__.py
flask_sspi/_common.py
flask_sspi/_wrappers.py
flask_sspi-0.3.dist-info/licenses/AUTHORS
flask_sspi-0.3.dist-info/licenses/LICENSE
flask_sspi_fake/__init__.py
flask_sspi_fake/_stubs.py
flask_sspi-0.3.dist-info/METADATA
flask_sspi-0.3.dist-info/WHEEL
flask_sspi-0.3.dist-info/top_level.txt
flask_sspi-0.3.dist-info/RECORD
