Metadata-Version: 2.4
Name: Flask-SSPI
Version: 0.3
Summary: SSPI authentication support for Flask
Author-email: ceprio <c.pypi@zone-c5.com>
License-Expression: BSD-3-Clause
Project-URL: Homepage, http://github.com/ceprio/flask-sspi
Project-URL: Documentation, http://github.com/ceprio/flask-sspi
Classifier: Development Status :: 4 - Beta
Classifier: Environment :: Web Environment
Classifier: Intended Audience :: Developers
Classifier: Operating System :: OS Independent
Classifier: Programming Language :: Python
Classifier: Topic :: Internet :: WWW/HTTP
Classifier: Topic :: Software Development :: Libraries :: Python Modules
Requires-Python: >=3.6
License-File: LICENSE
License-File: AUTHORS
Requires-Dist: Flask
Requires-Dist: pywin32
Dynamic: license-file
